{
 "sections": [
  {
   "id": "3be2c708-348b-7354-96a4-e5515d4f19a4",
   "title": "Learning Objective - Function Basics",
   "files": [
    {
     "path": "#tabs",
     "action": "close"
    }
   ],
   "layout": "1-panel",
   "path": [],
   "type": "markdown",
   "content-file": ".guides/content/Learning-Objective---Function-Basics-3be2.md",
   "chapter": false,
   "reset": [],
   "teacherOnly": false,
   "closeTerminalSession": true,
   "learningObjectives": ""
  },
  {
   "id": "24d2c736-382b-b2be-dc74-e23e891332f0",
   "title": "Function Definition",
   "files": [
    {
     "path": "#tabs",
     "action": "close"
    },
    {
     "path": "code/functions/call-function.py",
     "panel": 0,
     "action": "open"
    }
   ],
   "layout": "2-panels",
   "path": [],
   "type": "markdown",
   "content-file": ".guides/content/Function-Definition-24d2.md",
   "chapter": false,
   "reset": [],
   "teacherOnly": false,
   "closeTerminalSession": false,
   "learningObjectives": ""
  },
  {
   "id": "da333948-dca9-bf7c-6c4c-dcfeadf9d71d",
   "title": "Functions and Whitespace",
   "files": [
    {
     "path": "#tabs",
     "action": "close"
    },
    {
     "path": "code/functions/whitespace.py",
     "panel": 0,
     "action": "open"
    }
   ],
   "layout": "2-panels",
   "path": [],
   "type": "markdown",
   "content-file": ".guides/content/Functions-and-Whitespace-da33.md",
   "chapter": false,
   "reset": [],
   "teacherOnly": false,
   "closeTerminalSession": false,
   "learningObjectives": ""
  },
  {
   "id": "d8a7536c-aa98-ad83-3b0d-71feefa5a7d8",
   "title": "Docstring",
   "files": [
    {
     "path": "#tabs",
     "action": "close"
    },
    {
     "path": "code/functions/docstring.py",
     "panel": 0,
     "action": "open"
    }
   ],
   "layout": "2-panels",
   "path": [],
   "type": "markdown",
   "content-file": ".guides/content/Docstring-d8a7.md",
   "chapter": false,
   "reset": [],
   "teacherOnly": false,
   "closeTerminalSession": false,
   "learningObjectives": ""
  },
  {
   "id": "a8c8e349-c5ef-7638-46f2-bc8533f3e23e",
   "title": "When to Use a Function",
   "files": [
    {
     "path": "#tabs",
     "action": "close"
    },
    {
     "path": "#preview: https://{{domain3000}}/",
     "panel": 1,
     "action": "open"
    },
    {
     "path": "code/functions/when-functions.py",
     "panel": 0,
     "action": "open"
    }
   ],
   "layout": "3-cell",
   "path": [],
   "type": "markdown",
   "content-file": ".guides/content/When-to-Use-a-Function-a8c8.md",
   "chapter": false,
   "reset": [],
   "teacherOnly": false,
   "closeTerminalSession": false,
   "learningObjectives": ""
  },
  {
   "id": "844d9047-b10e-ab5b-2144-8d2e9d5f8fa8",
   "title": "Formative Assessment 1",
   "files": [
    {
     "path": "#tabs",
     "action": "close"
    }
   ],
   "layout": "1-panel",
   "path": [],
   "type": "markdown",
   "content-file": ".guides/content/Formative-Assessment-1-844d.md",
   "chapter": false,
   "reset": [],
   "teacherOnly": false,
   "closeTerminalSession": false,
   "learningObjectives": ""
  },
  {
   "id": "d4a338e0-c411-94d7-897a-0c798722d2f2",
   "title": "Formative Assessment 2",
   "files": [],
   "path": [],
   "type": "markdown",
   "content-file": ".guides/content/Formative-Assessment-2-d4a3.md",
   "chapter": false,
   "reset": [],
   "teacherOnly": false,
   "closeTerminalSession": true,
   "learningObjectives": ""
  },
  {
   "id": "f3d694f1-2557-5952-5991-446975f6871e",
   "title": "Learning Objective - Parameters",
   "files": [
    {
     "path": "#tabs",
     "action": "close"
    }
   ],
   "layout": "1-panel",
   "path": [],
   "type": "markdown",
   "content-file": ".guides/content/Learning-Objective---Parameters-f3d6.md",
   "chapter": false,
   "reset": [],
   "teacherOnly": false,
   "closeTerminalSession": true,
   "learningObjectives": ""
  },
  {
   "id": "6f8864f0-6d1d-59ad-d6d9-17b02f1a2374",
   "title": "Passing Parameters",
   "files": [
    {
     "path": "#tabs",
     "action": "close"
    },
    {
     "path": "code/functions/parameters.py",
     "panel": 0,
     "action": "open"
    }
   ],
   "layout": "2-panels",
   "path": [],
   "type": "markdown",
   "content-file": ".guides/content/Passing-Parameters-6f88.md",
   "chapter": false,
   "reset": [],
   "teacherOnly": false,
   "closeTerminalSession": false,
   "learningObjectives": ""
  },
  {
   "id": "f9421727-5516-d4f4-d65d-e421751966d7",
   "title": "Parameter Values",
   "files": [
    {
     "path": "#tabs",
     "action": "close"
    },
    {
     "path": "code/functions/parameter-values.py",
     "panel": 0,
     "action": "open"
    }
   ],
   "layout": "2-panels",
   "path": [],
   "type": "markdown",
   "content-file": ".guides/content/Parameter-Values-f942.md",
   "chapter": false,
   "reset": [],
   "teacherOnly": false,
   "closeTerminalSession": false,
   "learningObjectives": ""
  },
  {
   "id": "0b1b3c6f-207b-015c-aaa2-0c7300c245a4",
   "title": "Checking Parameters",
   "files": [
    {
     "path": "#tabs",
     "action": "close"
    },
    {
     "path": "code/functions/check-parameters.py",
     "panel": 0,
     "action": "open"
    }
   ],
   "layout": "2-panels",
   "path": [],
   "type": "markdown",
   "content-file": ".guides/content/Checking-Parameters-0b1b.md",
   "chapter": false,
   "reset": [],
   "teacherOnly": false,
   "closeTerminalSession": false,
   "learningObjectives": ""
  },
  {
   "id": "d14d770c-b7bb-2a58-4ca9-5937d42539b5",
   "title": "Parameters - Advanced Topics",
   "files": [
    {
     "path": "#tabs",
     "action": "close"
    },
    {
     "path": "code/functions/advanced-parameters.py",
     "panel": 0,
     "action": "open"
    }
   ],
   "layout": "2-panels",
   "path": [],
   "type": "markdown",
   "content-file": ".guides/content/Parameters---Advanced-Topics-d14d.md",
   "chapter": false,
   "reset": [],
   "teacherOnly": false,
   "closeTerminalSession": false,
   "learningObjectives": ""
  },
  {
   "id": "693e3540-748e-7e60-ace4-9b040b798a80",
   "title": "Formative Assessment 1",
   "files": [
    {
     "path": "#tabs",
     "action": "close"
    }
   ],
   "layout": "1-panel",
   "path": [],
   "type": "markdown",
   "content-file": ".guides/content/Formative-Assessment-1-693e.md",
   "chapter": false,
   "reset": [],
   "teacherOnly": false,
   "closeTerminalSession": false,
   "learningObjectives": ""
  },
  {
   "id": "1b463ac7-07ae-d3ee-2902-7e60b49626a9",
   "title": "Formative Assessment 2",
   "files": [
    {
     "path": "#tabs",
     "action": "close"
    }
   ],
   "layout": "1-panel",
   "path": [],
   "type": "markdown",
   "content-file": ".guides/content/Formative-Assessment-2-1b46.md",
   "chapter": false,
   "reset": [],
   "teacherOnly": false,
   "closeTerminalSession": false,
   "learningObjectives": ""
  },
  {
   "id": "ef663b36-c472-deb6-083e-3db7e8195c5e",
   "title": "Learning Objectives - Variable Scope",
   "files": [
    {
     "path": "#tabs",
     "action": "close"
    }
   ],
   "layout": "1-panel",
   "path": [],
   "type": "markdown",
   "content-file": ".guides/content/Learning-Objectives---Variable-Scope-ef66.md",
   "chapter": false,
   "reset": [],
   "teacherOnly": false,
   "closeTerminalSession": true,
   "learningObjectives": ""
  },
  {
   "id": "bb84d4a8-0a1a-2421-ea5c-285bbc041708",
   "title": "Local Scope",
   "files": [
    {
     "path": "#tabs",
     "action": "close"
    },
    {
     "path": "code/functions/local-scope.py",
     "panel": 0,
     "action": "open"
    }
   ],
   "layout": "2-panels",
   "path": [],
   "type": "markdown",
   "content-file": ".guides/content/Local-Scope-bb84.md",
   "chapter": false,
   "reset": [],
   "teacherOnly": false,
   "closeTerminalSession": false,
   "learningObjectives": ""
  },
  {
   "id": "4bcf08bd-f0a5-bce7-4afe-5f7b04493fa3",
   "title": "Global Scope",
   "files": [
    {
     "path": "#tabs",
     "action": "close"
    },
    {
     "path": "code/functions/global-scope.py",
     "panel": 0,
     "action": "open"
    }
   ],
   "layout": "2-panels",
   "path": [],
   "type": "markdown",
   "content-file": ".guides/content/Global-Scope-4bcf.md",
   "chapter": false,
   "reset": [],
   "teacherOnly": false,
   "closeTerminalSession": false,
   "learningObjectives": ""
  },
  {
   "id": "3bc0aa24-f2b9-61ea-93c2-b22c7f839ed2",
   "title": "Global vs Local Scope",
   "files": [
    {
     "path": "#tabs",
     "action": "close"
    },
    {
     "path": "code/functions/variable-scope.py",
     "panel": 0,
     "action": "open"
    }
   ],
   "layout": "2-panels",
   "path": [],
   "type": "markdown",
   "content-file": ".guides/content/Global-vs-Local-Scope-3bc0.md",
   "chapter": false,
   "reset": [],
   "teacherOnly": false,
   "closeTerminalSession": false,
   "learningObjectives": ""
  },
  {
   "id": "ec292a56-ef4b-5b00-7682-312605449e17",
   "title": "Formative Assessment 1",
   "files": [
    {
     "path": "#tabs",
     "action": "close"
    }
   ],
   "layout": "1-panel",
   "path": [],
   "type": "markdown",
   "content-file": ".guides/content/Formative-Assessment-1-ec29.md",
   "chapter": false,
   "reset": [],
   "teacherOnly": false,
   "closeTerminalSession": false,
   "learningObjectives": ""
  },
  {
   "id": "b780999d-2efe-d2f2-f615-ba404b778818",
   "title": "Formative Assessment 2",
   "files": [
    {
     "path": "#tabs",
     "action": "close"
    }
   ],
   "layout": "1-panel",
   "path": [],
   "type": "markdown",
   "content-file": ".guides/content/Formative-Assessment-2-b780.md",
   "chapter": false,
   "reset": [],
   "teacherOnly": false,
   "closeTerminalSession": false,
   "learningObjectives": ""
  },
  {
   "id": "6bb2a1c1-bfb2-9f96-dd40-50259acc9b10",
   "title": "Learning Objectives - Returning Values",
   "files": [
    {
     "path": "#tabs",
     "action": "close"
    }
   ],
   "layout": "1-panel",
   "path": [],
   "type": "markdown",
   "content-file": ".guides/content/Learning-Objectives---Returning-Values-6bb2.md",
   "chapter": false,
   "reset": [],
   "teacherOnly": false,
   "closeTerminalSession": true,
   "learningObjectives": ""
  },
  {
   "id": "ea327923-38a8-419e-b104-d8e314ee5a02",
   "title": "Returning Values",
   "files": [
    {
     "path": "#tabs",
     "action": "close"
    },
    {
     "path": "code/functions/returning-values.py",
     "panel": 0,
     "action": "open"
    }
   ],
   "layout": "2-panels",
   "path": [],
   "type": "markdown",
   "content-file": ".guides/content/Returning-Values-ea32.md",
   "chapter": false,
   "reset": [],
   "teacherOnly": false,
   "closeTerminalSession": false,
   "learningObjectives": ""
  },
  {
   "id": "94c47fc5-e9df-4275-1929-8f1b3e7daaf5",
   "title": "Side Effects",
   "files": [
    {
     "path": "#tabs",
     "action": "close"
    },
    {
     "path": "code/functions/side-effects.py",
     "panel": 0,
     "action": "open"
    }
   ],
   "layout": "2-panels",
   "path": [],
   "type": "markdown",
   "content-file": ".guides/content/Side-Effects-94c4.md",
   "chapter": false,
   "reset": [],
   "teacherOnly": false,
   "closeTerminalSession": false,
   "learningObjectives": ""
  },
  {
   "id": "77811257-4fe4-4dc0-c40b-ca3378bba01b",
   "title": "Formative Assessment 1",
   "files": [
    {
     "path": "#tabs",
     "action": "close"
    }
   ],
   "layout": "1-panel",
   "path": [],
   "type": "markdown",
   "content-file": ".guides/content/Formative-Assessment-1-7781.md",
   "chapter": false,
   "reset": [],
   "teacherOnly": false,
   "closeTerminalSession": false,
   "learningObjectives": ""
  },
  {
   "id": "3a1f9986-7f1b-f869-f549-555834d2c7ce",
   "title": "Formative Assessment 2",
   "files": [
    {
     "path": "#tabs",
     "action": "close"
    }
   ],
   "layout": "1-panel",
   "path": [],
   "type": "markdown",
   "content-file": ".guides/content/Formative-Assessment-2-3a1f.md",
   "chapter": false,
   "reset": [],
   "teacherOnly": false,
   "closeTerminalSession": false,
   "learningObjectives": ""
  },
  {
   "id": "2e79cd00-fe10-a09c-d556-64a2cefdaa9b",
   "title": "Learning Objectives - Function Composition",
   "files": [
    {
     "path": "#tabs",
     "action": "close"
    }
   ],
   "layout": "1-panel",
   "path": [],
   "type": "markdown",
   "content-file": ".guides/content/Learning-Objectives---Function-Composition-2e79.md",
   "chapter": false,
   "reset": [],
   "teacherOnly": false,
   "closeTerminalSession": true,
   "learningObjectives": ""
  },
  {
   "id": "4711cfba-c68a-e050-edb1-d211233dfd3d",
   "title": "Helper Functions",
   "files": [
    {
     "path": "#tabs",
     "action": "close"
    },
    {
     "path": "code/functions/helper-functions.py",
     "panel": 0,
     "action": "open"
    }
   ],
   "layout": "2-panels",
   "path": [],
   "type": "markdown",
   "content-file": ".guides/content/Helper-Functions-4711.md",
   "chapter": false,
   "reset": [],
   "teacherOnly": false,
   "closeTerminalSession": false,
   "learningObjectives": ""
  },
  {
   "id": "ec3229fa-7e8d-f58d-caa0-71fbf74c6d9e",
   "title": "Function Composition",
   "files": [
    {
     "path": "#tabs",
     "action": "close"
    },
    {
     "path": "code/functions/function-composition.py",
     "panel": 0,
     "action": "open"
    }
   ],
   "layout": "2-panels",
   "path": [],
   "type": "markdown",
   "content-file": ".guides/content/Function-Composition-ec32.md",
   "chapter": false,
   "reset": [],
   "teacherOnly": false,
   "closeTerminalSession": false,
   "learningObjectives": ""
  },
  {
   "id": "92aed5cd-48f4-86fa-3b2f-af0863789d8f",
   "title": "Modularity",
   "files": [
    {
     "path": "#tabs",
     "action": "close"
    },
    {
     "path": "#preview: https://{{domain3000}}/",
     "panel": 1,
     "action": "open"
    },
    {
     "path": "code/functions/modularity.py",
     "panel": 0,
     "action": "open"
    }
   ],
   "layout": "3-cell",
   "path": [],
   "type": "markdown",
   "content-file": ".guides/content/Modularity-92ae.md",
   "chapter": false,
   "reset": [],
   "teacherOnly": false,
   "closeTerminalSession": false,
   "learningObjectives": ""
  },
  {
   "id": "59df77f5-3e06-2a1c-fdbf-20afc9175aae",
   "title": "Formative Assessment 1",
   "files": [
    {
     "path": "#tabs",
     "action": "close"
    }
   ],
   "layout": "1-panel",
   "path": [],
   "type": "markdown",
   "content-file": ".guides/content/Formative-Assessment-1-59df.md",
   "chapter": false,
   "reset": [],
   "teacherOnly": false,
   "closeTerminalSession": false,
   "learningObjectives": ""
  },
  {
   "id": "b0efe1f8-2daf-7ef9-10e3-e5a7ebbb2574",
   "title": "Formative Assessment 2",
   "files": [
    {
     "path": "#tabs",
     "action": "close"
    }
   ],
   "layout": "1-panel",
   "path": [],
   "type": "markdown",
   "content-file": ".guides/content/Formative-Assessment-2-b0ef.md",
   "chapter": false,
   "reset": [],
   "teacherOnly": false,
   "closeTerminalSession": false,
   "learningObjectives": ""
  },
  {
   "id": "ac6ec42b-99a9-3716-7cb5-7daa333a6f45",
   "title": "Lab 1",
   "files": [
    {
     "path": "#tabs",
     "action": "close"
    },
    {
     "path": "code/functions/movie-app.py",
     "panel": 0,
     "action": "open"
    }
   ],
   "layout": "2-panels",
   "path": [],
   "type": "markdown",
   "content-file": ".guides/content/Lab-1-ac6e.md",
   "chapter": false,
   "reset": [],
   "teacherOnly": false,
   "closeTerminalSession": false,
   "learningObjectives": ""
  },
  {
   "id": "77a716ef-8999-d62b-a356-0502574079ea",
   "title": "Lab 2",
   "files": [
    {
     "path": "#tabs",
     "action": "close"
    },
    {
     "path": "code/functions/movie-app.py",
     "panel": 0,
     "action": "open"
    }
   ],
   "layout": "2-panels",
   "path": [],
   "type": "markdown",
   "content-file": ".guides/content/Lab-2-77a7.md",
   "chapter": false,
   "reset": [],
   "teacherOnly": false,
   "closeTerminalSession": false,
   "learningObjectives": ""
  },
  {
   "id": "50f6eaef-98de-ac5f-01cb-d9d8110df3b3",
   "title": "Lab 3",
   "files": [
    {
     "path": "#tabs",
     "action": "close"
    },
    {
     "path": "code/functions/movie-app.py",
     "panel": 0,
     "action": "open"
    }
   ],
   "layout": "2-panels",
   "path": [],
   "type": "markdown",
   "content-file": ".guides/content/Lab-3-50f6.md",
   "chapter": false,
   "reset": [],
   "teacherOnly": false,
   "closeTerminalSession": false,
   "learningObjectives": ""
  },
  {
   "id": "928ecbee-d769-4576-9786-3ceb9ed306b3",
   "title": "Lab 4",
   "files": [
    {
     "path": "#tabs",
     "action": "close"
    },
    {
     "path": "code/functions/movie-app.py",
     "panel": 0,
     "action": "open"
    }
   ],
   "layout": "2-panels",
   "path": [],
   "type": "markdown",
   "content-file": ".guides/content/Lab-4-928e.md",
   "chapter": false,
   "reset": [],
   "teacherOnly": false,
   "closeTerminalSession": false,
   "learningObjectives": ""
  },
  {
   "id": "f186c624-341c-f3da-39d5-0fc4e9a2b05f",
   "title": "Lab 5",
   "files": [
    {
     "path": "#tabs",
     "action": "close"
    },
    {
     "path": "code/functions/movie-app.py",
     "panel": 0,
     "action": "open"
    }
   ],
   "layout": "2-panels",
   "path": [],
   "type": "markdown",
   "content-file": ".guides/content/Lab-5-f186.md",
   "chapter": false,
   "reset": [],
   "teacherOnly": false,
   "closeTerminalSession": false,
   "learningObjectives": ""
  },
  {
   "id": "ac0afdd8-1828-ae91-55dc-8cc9e8e2a05d",
   "title": "Lab Challenge",
   "files": [
    {
     "path": "#tabs",
     "action": "close"
    },
    {
     "path": "code/functions/lab_challenge.py",
     "panel": 0,
     "action": "open"
    }
   ],
   "layout": "2-panels",
   "path": [],
   "type": "markdown",
   "content-file": ".guides/content/Lab-Challenge-ac0a.md",
   "chapter": false,
   "reset": [],
   "teacherOnly": false,
   "closeTerminalSession": false,
   "learningObjectives": ""
  },
  {
   "id": "3350703c-e828-b87f-dfb9-dc726317b210",
   "title": "Exercise 1",
   "files": [
    {
     "path": "#tabs",
     "action": "close"
    },
    {
     "path": "code/functions/exercise1.py",
     "panel": 0,
     "action": "open"
    }
   ],
   "layout": "2-panels",
   "path": [],
   "type": "markdown",
   "content-file": ".guides/content/Exercise-1-3350.md",
   "chapter": false,
   "reset": [],
   "teacherOnly": false,
   "closeTerminalSession": false,
   "learningObjectives": ""
  },
  {
   "id": "2ed30cf2-3af3-c8e1-54f2-6e292a5df4b1",
   "title": "Exercise 2",
   "files": [
    {
     "path": "#tabs",
     "action": "close"
    },
    {
     "path": "code/functions/exercise2.py",
     "panel": 0,
     "action": "open"
    }
   ],
   "layout": "2-panels",
   "path": [],
   "type": "markdown",
   "content-file": ".guides/content/Exercise-2-2ed3.md",
   "chapter": false,
   "reset": [],
   "teacherOnly": false,
   "closeTerminalSession": false,
   "learningObjectives": ""
  },
  {
   "id": "ae9275c8-d5ff-cc30-f1e1-7a491953ced4",
   "title": "Exercise 3",
   "files": [
    {
     "path": "#tabs",
     "action": "close"
    },
    {
     "path": "code/functions/exercise3.py",
     "panel": 0,
     "action": "open"
    }
   ],
   "layout": "2-panels",
   "path": [],
   "type": "markdown",
   "content-file": ".guides/content/Exercise-3-ae92.md",
   "chapter": false,
   "reset": [],
   "teacherOnly": false,
   "closeTerminalSession": false,
   "learningObjectives": ""
  },
  {
   "id": "b965e0ed-a837-b3b3-2c77-83779a994c53",
   "title": "Exercise 4",
   "files": [
    {
     "path": "#tabs",
     "action": "close"
    },
    {
     "path": "code/functions/exercise4.py",
     "panel": 0,
     "action": "open"
    }
   ],
   "layout": "2-panels",
   "path": [],
   "type": "markdown",
   "content-file": ".guides/content/Exercise-4-b965.md",
   "chapter": false,
   "reset": [],
   "teacherOnly": false,
   "closeTerminalSession": false,
   "learningObjectives": ""
  },
  {
   "id": "cac2eaa7-8e40-beef-543e-da13202d9843",
   "title": "Exercise 5",
   "files": [
    {
     "path": "#tabs",
     "action": "close"
    },
    {
     "path": "code/functions/exercise5.py",
     "panel": 0,
     "action": "open"
    }
   ],
   "layout": "2-panels",
   "path": [],
   "type": "markdown",
   "content-file": ".guides/content/Exercise-5-cac2.md",
   "chapter": false,
   "reset": [],
   "teacherOnly": false,
   "closeTerminalSession": false,
   "learningObjectives": ""
  }
 ],
 "theme": "light",
 "scripts": [],
 "lexikonTopic": "",
 "suppressPageNumbering": true,
 "useSubmitButtons": true,
 "useMarkAsComplete": true,
 "hideMenu": true,
 "allowGuideClose": false,
 "collapsedOnStart": false,
 "hideSectionsToggle": false,
 "hideBackToDashboard": false,
 "protectLayout": false
}